lucky_choice_jinli/__init__.py
lucky_choice_jinli/jinli.py
lucky_choice_jinli_v1-0.0.3.dist-info/LICENSE
lucky_choice_jinli_v1-0.0.3.dist-info/METADATA
lucky_choice_jinli_v1-0.0.3.dist-info/WHEEL
lucky_choice_jinli_v1-0.0.3.dist-info/top_level.txt
lucky_choice_jinli_v1-0.0.3.dist-info/RECORD
