Metadata-Version: 2.1
Name: lucky-choice-jinli-v1
Version: 0.0.3
Summary: make a choice
Home-page: https://github.com/pypa/sampleproject
Author: jimmy
Author-email: jimmy@example.com
License: UNKNOWN
Platform: UNKNOWN
Classifier: Programming Language :: Python :: 3
Classifier: License :: OSI Approved :: MIT License
Classifier: Operating System :: OS Independent
